api/__init__.py
api/models.py
rottentomatoes/__init__.py
rottentomatoes/exceptions.py
rottentomatoes/movie.py
rottentomatoes/search.py
rottentomatoes/standalone.py
rottentomatoes/utils.py
tests/__init__.py
tests/conftest.py
tests/test_movie.py
tests/test_standalone.py
rottentomatoes_python-1.2.0.dist-info/METADATA
rottentomatoes_python-1.2.0.dist-info/WHEEL
rottentomatoes_python-1.2.0.dist-info/top_level.txt
rottentomatoes_python-1.2.0.dist-info/RECORD
