Metadata-Version: 2.1
Name: rottentomatoes-python
Version: 1.2.0
Summary: Scrape Rotten Tomatoes's website for basic information on movies, without the use of their hard-to-attain official REST API.
Home-page: https://github.com/preritdas/rottentomatoes-python
Author: Prerit Das
Author-email: <preritdas@gmail.com>
Keywords: python,movies,rottentomatoes
Classifier: Programming Language :: Python :: 3
Classifier: Operating System :: Unix
Classifier: Operating System :: MacOS :: MacOS X
Classifier: Operating System :: Microsoft :: Windows
Requires-Dist: requests
Requires-Dist: beautifulsoup4
